fidmaa_gui/QClickableLabel.py
fidmaa_gui/app.py
fidmaa_gui/calculations.py
fidmaa_gui/const.py
fidmaa_gui/entrypoints.py
fidmaa_gui/errors.py
fidmaa_gui/form.ui
fidmaa_gui-0.1.2.dist-info/LICENSE
fidmaa_gui-0.1.2.dist-info/METADATA
fidmaa_gui-0.1.2.dist-info/WHEEL
fidmaa_gui-0.1.2.dist-info/entry_points.txt
fidmaa_gui-0.1.2.dist-info/RECORD
