Metadata-Version: 2.1
Name: fidmaa-gui
Version: 0.1.2
Summary: What's FIDMAA?
License: MIT
Author: Michał Pasternak
Author-email: michal.dtz@gmail.com
Requires-Python: >=3.12,<3.13
Classifier: License :: OSI Approved :: MIT License
Classifier: Programming Language :: Python :: 3
Classifier: Programming Language :: Python :: 3.12
Requires-Dist: Pillow (>=10.2.0,<11.0.0)
Requires-Dist: PySide6 (>=6.6.2,<7.0.0)
Requires-Dist: beautifulsoup4 (>=4.11.1,<5.0.0)
Requires-Dist: numpy (>=1.23.5,<2.0.0)
Requires-Dist: opencv-python (>=4.6.0.66,<5.0.0.0)
Requires-Dist: piexif (>=1.1.3,<2.0.0)
Requires-Dist: portrait-analyser (>=0.1.2,<0.2.0)
Requires-Dist: pyheif-iplweb (>=0.7.1.dev1176,<0.8.0)
